odoo/addons/stock_lot_on_hand_first/README.rst
odoo/addons/stock_lot_on_hand_first/__init__.py
odoo/addons/stock_lot_on_hand_first/__manifest__.py
odoo/addons/stock_lot_on_hand_first/i18n/es.po
odoo/addons/stock_lot_on_hand_first/i18n/it.po
odoo/addons/stock_lot_on_hand_first/i18n/stock_lot_on_hand_first.pot
odoo/addons/stock_lot_on_hand_first/models/__init__.py
odoo/addons/stock_lot_on_hand_first/models/stock_lot.py
odoo/addons/stock_lot_on_hand_first/models/stock_move.py
odoo/addons/stock_lot_on_hand_first/models/stock_move_line.py
odoo/addons/stock_lot_on_hand_first/models/stock_picking.py
odoo/addons/stock_lot_on_hand_first/models/stock_picking_type.py
odoo/addons/stock_lot_on_hand_first/readme/CONFIGURE.md
odoo/addons/stock_lot_on_hand_first/readme/CONTRIBUTORS.md
odoo/addons/stock_lot_on_hand_first/readme/DESCRIPTION.md
odoo/addons/stock_lot_on_hand_first/static/description/icon.png
odoo/addons/stock_lot_on_hand_first/static/description/index.html
odoo/addons/stock_lot_on_hand_first/tests/__init__.py
odoo/addons/stock_lot_on_hand_first/tests/test_lot_on_hand_first.py
odoo/addons/stock_lot_on_hand_first/views/stock_move.xml
odoo/addons/stock_lot_on_hand_first/views/stock_move_line.xml
odoo/addons/stock_lot_on_hand_first/views/stock_picking.xml
odoo/addons/stock_lot_on_hand_first/views/stock_picking_type.xml
odoo_addon_stock_lot_on_hand_first-17.0.1.0.0.7.dist-info/METADATA
odoo_addon_stock_lot_on_hand_first-17.0.1.0.0.7.dist-info/WHEEL
odoo_addon_stock_lot_on_hand_first-17.0.1.0.0.7.dist-info/top_level.txt
odoo_addon_stock_lot_on_hand_first-17.0.1.0.0.7.dist-info/RECORD
