Metadata-Version: 2.1
Name: odoo-addon-stock_lot_on_hand_first
Version: 17.0.1.0.0.7
Requires-Python: >=3.10
Requires-Dist: odoo-addon-base_view_inheritance_extension>=17.0dev,<17.1dev
Requires-Dist: odoo>=17.0a,<17.1dev
Summary: Allows to display lots on hand first in M2o fields
Home-page: https://github.com/OCA/stock-logistics-workflow
License: AGPL-3
Author: Camptocamp, Odoo Community Association (OCA)
Author-email: support@odoo-community.org
Classifier: Programming Language :: Python
Classifier: Framework :: Odoo
Classifier: Framework :: Odoo :: 17.0
Classifier: License :: OSI Approved :: GNU Affero General Public License v3
Classifier: Development Status :: 3 - Alpha
